console_player_noffmpeg-1.2.1.dist-info/licenses/LICENSE
consolepic/__main__.py
consoleplay/__init__.py
consoleplay/__main__.py
consoleplay/icon.png
cpvgen/__main__.py
cpvgen/gen.py
console_player_noffmpeg-1.2.1.dist-info/METADATA
console_player_noffmpeg-1.2.1.dist-info/WHEEL
console_player_noffmpeg-1.2.1.dist-info/entry_points.txt
console_player_noffmpeg-1.2.1.dist-info/top_level.txt
console_player_noffmpeg-1.2.1.dist-info/RECORD
