Metadata-Version: 2.4
Name: console-player-noffmpeg
Version: 1.2.1
Summary: 让终端可以播放视频！
Home-page: https://github.com/SystemFileB/console-player
Author: SystemFileB
License: LGPLv3
Platform: Windows
Classifier: Programming Language :: Python :: 3
Classifier: License :: OSI Approved :: Mozilla Public License 2.0 (MPL 2.0)
License-File: LICENSE
Requires-Dist: py7zr
Requires-Dist: tqdm
Requires-Dist: Pillow
Requires-Dist: colorama
Requires-Dist: pygame
Dynamic: author
Dynamic: classifier
Dynamic: description
Dynamic: description-content-type
Dynamic: home-page
Dynamic: license
Dynamic: license-file
Dynamic: platform
Dynamic: requires-dist
Dynamic: summary
